MANIFEST.in
README.md
VERSION
requirements.txt
setup.cfg
setup.py
bin/cloud-run-compose
cloud_run_compose/__init__.py
cloud_run_compose/__main__.py
cloud_run_compose/down.py
cloud_run_compose/generate_terraform.py
cloud_run_compose/logger.py
cloud_run_compose/support.py
cloud_run_compose/up.py
cloud_run_compose.egg-info/PKG-INFO
cloud_run_compose.egg-info/SOURCES.txt
cloud_run_compose.egg-info/dependency_links.txt
cloud_run_compose.egg-info/requires.txt
cloud_run_compose.egg-info/top_level.txt