Metadata-Version: 2.1
Name: cloud-run-compose
Version: 1.0.5
Summary: cloud-run-compose
Home-page: https://github.com/remorses/cloud-run-compose
Author: Tommaso De Rossi
Author-email: daer.tommy@gmail.com
License: Apache Software License 2.0
Keywords: TODO
Platform: UNKNOWN
Classifier: Intended Audience :: Information Technology
Classifier: Programming Language :: Python :: 3
Classifier: Programming Language :: Python :: 3.6
Classifier: Programming Language :: Python :: 3.7
